odoo/addons/odoo_project_migration/README.rst
odoo/addons/odoo_project_migration/__init__.py
odoo/addons/odoo_project_migration/__manifest__.py
odoo/addons/odoo_project_migration/migrations/16.0.1.1.0/post-migration.py
odoo/addons/odoo_project_migration/models/__init__.py
odoo/addons/odoo_project_migration/models/odoo_module_branch_migration.py
odoo/addons/odoo_project_migration/models/odoo_project.py
odoo/addons/odoo_project_migration/models/odoo_project_module.py
odoo/addons/odoo_project_migration/models/odoo_project_module_migration.py
odoo/addons/odoo_project_migration/readme/CONTRIBUTORS.md
odoo/addons/odoo_project_migration/readme/DESCRIPTION.md
odoo/addons/odoo_project_migration/security/ir.model.access.csv
odoo/addons/odoo_project_migration/static/description/icon.png
odoo/addons/odoo_project_migration/static/description/index.html
odoo/addons/odoo_project_migration/views/odoo_module_branch_migration.xml
odoo/addons/odoo_project_migration/views/odoo_project.xml
odoo/addons/odoo_project_migration/views/odoo_project_module_migration.xml
odoo/addons/odoo_project_migration/wizards/__init__.py
odoo/addons/odoo_project_migration/wizards/export_migration_report.py
odoo/addons/odoo_project_migration/wizards/export_migration_report.xml
odoo/addons/odoo_project_migration/wizards/generate_migration_data.py
odoo/addons/odoo_project_migration/wizards/generate_migration_data.xml
odoo_addon_odoo_project_migration-16.0.1.1.1.dist-info/METADATA
odoo_addon_odoo_project_migration-16.0.1.1.1.dist-info/WHEEL
odoo_addon_odoo_project_migration-16.0.1.1.1.dist-info/top_level.txt
odoo_addon_odoo_project_migration-16.0.1.1.1.dist-info/RECORD
